mehdashti_rate_limit/__init__.py
mehdashti_rate_limit/base.py
mehdashti_rate_limit/decorators.py
mehdashti_rate_limit/memory.py
mehdashti_rate_limit/middleware.py
mehdashti_rate_limit/redis.py
mehdashti_rate_limit-0.1.1.dist-info/METADATA
mehdashti_rate_limit-0.1.1.dist-info/WHEEL
mehdashti_rate_limit-0.1.1.dist-info/RECORD
