Metadata-Version: 2.4
Name: mehdashti-rate-limit
Version: 0.1.1
Summary: Rate limiting utilities with Redis and Memory providers for Smart Platform
Author-email: Mahdi Ashti <mahdi@mehdashti.com>
License: MIT
Keywords: fastapi,rate-limit,redis,throttle
Classifier: Development Status :: 4 - Beta
Classifier: Intended Audience :: Developers
Classifier: License :: OSI Approved :: MIT License
Classifier: Programming Language :: Python :: 3
Classifier: Programming Language :: Python :: 3.13
Requires-Python: >=3.13
Requires-Dist: fastapi>=0.104.0
Requires-Dist: redis>=5.0.0
Provides-Extra: dev
Requires-Dist: httpx>=0.25.0; extra == 'dev'
Requires-Dist: pytest-asyncio>=0.21.0; extra == 'dev'
Requires-Dist: pytest>=7.4.0; extra == 'dev'
